polaris/__init__.py
polaris/sha.txt
polaris/version.py
polaris/analyze/__init__.py
polaris/analyze/activity_metrics.py
polaris/analyze/demand_report.py
polaris/analyze/demand_table_metrics.py
polaris/analyze/energy_metrics.py
polaris/analyze/kpi_comparator.py
polaris/analyze/kpi_utils.py
polaris/analyze/path_metrics.py
polaris/analyze/popsyn_analysis.py
polaris/analyze/result_kpis.py
polaris/analyze/spatial_metrics.py
polaris/analyze/tnc_metrics.py
polaris/analyze/transit_demand_metrics.py
polaris/analyze/transit_supply_metrics.py
polaris/analyze/trip_metrics.py
polaris/analyze/mapping/flow_lines.py
polaris/analyze/mapping/utils.py
polaris/bin/Batch_Router.dll
polaris/bin/Batch_Router_Exe.exe
polaris/bin/BirthsAndDeaths.exe
polaris/bin/Core_Tests.exe
polaris/bin/Hello_World.exe
polaris/bin/Integrated_Model.exe
polaris/bin/LicenseHandler.dll
polaris/bin/Scratch.exe
polaris/bin/git.sha
polaris/bin/hdf5.dll
polaris/bin/hdf5_hl.dll
polaris/bin/licenses/glpk.txt
polaris/bin/licenses/hdf5.txt
polaris/bin/licenses/log4cpp.txt
polaris/bin/licenses/odb.txt
polaris/bin/licenses/or-tools.txt
polaris/bin/licenses/sqlite.txt
polaris/demand/__init__.py
polaris/demand/demand.py
polaris/demand/checker/__init__.py
polaris/demand/checker/crashing_queries.sql
polaris/demand/checker/demand_checker.py
polaris/demand/database/__init__.py
polaris/demand/database/summary.py
polaris/demand/database/default_values/Activity_Type.csv
polaris/demand/database/default_values/Activity_Type.schema
polaris/demand/database/default_values/Automation_Type.csv
polaris/demand/database/default_values/Automation_Type.schema
polaris/demand/database/default_values/Connectivity_Type.csv
polaris/demand/database/default_values/Connectivity_Type.schema
polaris/demand/database/default_values/EV_Features.csv
polaris/demand/database/default_values/EV_Features.schema
polaris/demand/database/default_values/Fuel_Type.csv
polaris/demand/database/default_values/Fuel_Type.schema
polaris_studio-2025.12.45.dist-info/licenses/LICENSE.md
polaris_studio-2025.12.45.dist-info/METADATA
polaris_studio-2025.12.45.dist-info/WHEEL
polaris_studio-2025.12.45.dist-info/entry_points.txt
polaris_studio-2025.12.45.dist-info/top_level.txt
polaris_studio-2025.12.45.dist-info/RECORD
